{
  "batch89": [
    {
      "Trae Session ID": "session_441",
      "轮次": "第一轮",
      "User Prompt": "使用 Canvas 开发图片马赛克工具，用户上传图片，鼠标拖拽选择区域，应用马赛克效果（像素化），支持撤销。",
      "任务类型": "0-1代码生成",
      "业务领域": "Web前端",
      "修改范围": "模块内多文件",
      "任务是否完成": "未完成任务",
      "产物及过程是否满意": "不满意",
      "不满意原因": "产物不满意：未说明马赛克的粒度（像素块大小 10x10），复现条件为块大小过大失真，代码示例需可配置粒度，未实现区域选择的矩形框预览，遗漏马赛克后边缘的羽化，未提供保存图片功能。",
      "github地址": "https://github.com/xiaoyu-li-china/test_dogfooding/tree/main/packages",
      "分支/文件夹": "master",
      "截图（产物/运行结果/对话）": "[图片]",
      "日志轨迹": "未提供详细日志轨迹，见截图"
    },
    {
      "Trae Session ID": "session_442",
      "轮次": "第二轮",
      "User Prompt": "修复马赛克应用后撤销导致其他区域也被清除，以及高分辨率图片处理时内存溢出（canvas 尺寸限制）。",
      "任务类型": "Bug修复",
      "业务领域": "Web前端",
      "修改范围": "模块内多文件",
      "任务是否完成": "未完成任务",
      "产物及过程是否满意": "不满意",
      "不满意原因": "产物不满意：未明确降采样对马赛克效果的影响（原图缩小后块更粗），复现条件为原始图片 8000x6000，代码示例需警告用户，未实现区域的坐标缩放（降采样后映射），遗漏取消选择的功能，未测试多次马赛克叠加的撤销栈。",
      "github地址": "https://github.com/xiaoyu-li-china/test_dogfooding/tree/main/packages",
      "分支/文件夹": "master",
      "截图（产物/运行结果/对话）": "[图片]",
      "日志轨迹": "未提供详细日志轨迹，见截图"
    },
    {
      "Trae Session ID": "session_443",
      "轮次": "第三轮",
      "User Prompt": "增加马赛克形状（圆形、六边形），以及实时预览（滑块调整粒度）。",
      "任务类型": "Feature迭代",
      "业务领域": "Web前端",
      "修改范围": "模块内多文件",
      "任务是否完成": "未完成任务",
      "产物及过程是否满意": "不满意",
      "不满意原因": "产物不满意：未说明六边形马赛克的渲染算法（六边形网格），复现条件为边界对齐问题，代码示例需计算六边形覆盖，未实现粒度的渐变过渡（连续调整），遗漏形状预览的缩略图，未提供自定义形状的上传（SVG 模板）。",
      "github地址": "https://github.com/xiaoyu-li-china/test_dogfooding/tree/main/packages",
      "分支/文件夹": "master",
      "截图（产物/运行结果/对话）": "[图片]",
      "日志轨迹": "未提供详细日志轨迹，见截图"
    },
    {
      "Trae Session ID": "session_444",
      "轮次": "第四轮",
      "User Prompt": "使用 Jest 测试马赛克算法（像素块替换），模拟 ImageData 输入输出。",
      "任务类型": "代码测试",
      "业务领域": "Web前端",
      "修改范围": "模块内多文件",
      "任务是否完成": "未完成任务",
      "产物及过程是否满意": "不满意",
      "不满意原因": "产物不满意：未说明测试中 ImageData 的构造（`Uint8ClampedArray`），复现条件为长宽非整数倍，代码示例需处理边界，未测试圆形马赛克的边界像素，遗漏撤销栈的状态快照测试，未提供大图的性能基准。",
      "github地址": "https://github.com/xiaoyu-li-china/test_dogfooding/tree/main/packages",
      "分支/文件夹": "master",
      "截图（产物/运行结果/对话）": "[图片]",
      "日志轨迹": "未提供详细日志轨迹，见截图"
    },
    {
      "Trae Session ID": "session_445",
      "轮次": "第五轮",
      "User Prompt": "解释 Canvas 中 `getImageData` 和 `putImageData` 的性能（避免每帧调用），以及如何实现马赛克的块平均算法。给出平均 10x10 块的代码。",
      "任务类型": "代码理解",
      "业务领域": "Web前端",
      "修改范围": "代码理解文档",
      "任务是否完成": "未完成任务",
      "产物及过程是否满意": "不满意",
      "不满意原因": "产物不满意：未明确平均值计算的浮点舍入（整数颜色），复现条件为精细图像，代码示例需使用整数运算，未解释 `createImageData` 复用对象，遗漏块处理时的边缘回绕，未提供 Web Worker 离屏渲染。",
      "github地址": "https://github.com/xiaoyu-li-china/test_dogfooding/tree/main/packages",
      "分支/文件夹": "master",
      "截图（产物/运行结果/对话）": "[图片]",
      "日志轨迹": "未提供详细日志轨迹，见截图"
    }
  ],
  "batch90": [
    {
      "Trae Session ID": "session_446",
      "轮次": "第一轮",
      "User Prompt": "使用 Unity Animator 实现角色动画状态机，包含 Idle、Walk、Run、Jump 状态，设置转换条件（速度参数、按空格），跳跃后落地自动回到 Idle。",
      "任务类型": "0-1代码生成",
      "业务领域": "游戏开发",
      "修改范围": "模块内多文件",
      "任务是否完成": "未完成任务",
      "产物及过程是否满意": "不满意",
      "不满意原因": "产物不满意：未说明跳跃动画的 exit time（未播放完毕不能再次跳跃），复现条件为连续按空格导致动画打断，代码示例需设置 `Has Exit Time`，未实现 Run 到 Idle 的平滑过渡，遗漏跳跃落地时的过渡（`Any State` 到 Idle），未提供动画的根运动（Root Motion）配置。",
      "github地址": "https://github.com/xiaoyu-li-china/test_dogfooding/tree/main/packages",
      "分支/文件夹": "master",
      "截图（产物/运行结果/对话）": "[图片]",
      "日志轨迹": "未提供详细日志轨迹，见截图"
    },
    {
      "Trae Session ID": "session_447",
      "轮次": "第二轮",
      "User Prompt": "修复从 Run 切换到 Idle 时动画卡顿（混合时间过短），以及跳跃动画在空中时再次按空格导致二次跳跃。",
      "任务类型": "Bug修复",
      "业务领域": "游戏开发",
      "修改范围": "模块内多文件",
      "任务是否完成": "未完成任务",
      "产物及过程是否满意": "不满意",
      "不满意原因": "产物不满意：未明确禁用二次跳跃的变量（`isJumping`），复现条件为长按空格，代码示例需在状态机中用 `bool` 参数，未实现地面检测（`IsGrounded`），遗漏动画事件（落地时播放粒子），未测试斜坡上的动画过渡。",
      "github地址": "https://github.com/xiaoyu-li-china/test_dogfooding/tree/main/packages",
      "分支/文件夹": "master",
      "截图（产物/运行结果/对话）": "[图片]",
      "日志轨迹": "未提供详细日志轨迹，见截图"
    },
    {
      "Trae Session ID": "session_448",
      "轮次": "第三轮",
      "User Prompt": "增加技能动画（攻击、施法），使用 `AnimatorOverrideController` 换装，以及动画融合（头部层只控制表情）。",
      "任务类型": "Feature迭代",
      "业务领域": "游戏开发",
      "修改范围": "模块内多文件",
      "任务是否完成": "未完成任务",
      "产物及过程是否满意": "不满意",
      "不满意原因": "产物不满意：未说明动画层（Layer）的权重和遮罩（Avatar Mask），复现条件为表情与身体动作冲突，代码示例需设置 `Additive` 模式，未实现武器切换时的动态 Override，遗漏技能动画的打断优先级，未提供动画曲线控制特效时间点。",
      "github地址": "https://github.com/xiaoyu-li-china/test_dogfooding/tree/main/packages",
      "分支/文件夹": "master",
      "截图（产物/运行结果/对话）": "[图片]",
      "日志轨迹": "未提供详细日志轨迹，见截图"
    },
    {
      "Trae Session ID": "session_449",
      "轮次": "第四轮",
      "User Prompt": "编写单元测试测试动画参数的设置（`SetFloat`），使用 `Animator` 的 mock。",
      "任务类型": "代码测试",
      "业务领域": "游戏开发",
      "修改范围": "模块内多文件",
      "任务是否完成": "未完成任务",
      "产物及过程是否满意": "不满意",
      "不满意原因": "产物不满意：未说明测试中需要模拟 Animator 的 Update，复现条件为依赖帧更新，代码示例使用 `Animator.Update(deltaTime)` 手动推进，未测试 OverrideController 的替换，遗漏跳跃状态的判断（`GetCurrentAnimatorStateInfo`），未提供动画事件的回调测试。",
      "github地址": "https://github.com/xiaoyu-li-china/test_dogfooding/tree/main/packages",
      "分支/文件夹": "master",
      "截图（产物/运行结果/对话）": "[图片]",
      "日志轨迹": "未提供详细日志轨迹，见截图"
    },
    {
      "Trae Session ID": "session_450",
      "轮次": "第五轮",
      "User Prompt": "解释 Unity 的动画状态机过渡条件（参数、Exit Time），以及 `AnimatorOverrideController` 的用途。给出运行时修改攻击动画的代码。",
      "任务类型": "代码理解",
      "业务领域": "游戏开发",
      "修改范围": "代码理解文档",
      "任务是否完成": "未完成任务",
      "产物及过程是否满意": "不满意",
      "不满意原因": "产物不满意：未明确 OverrideController 的资源加载（`Resources.Load`），复现条件为动画未预加载，代码示例需异步加载，未解释 `AvatarMask` 的层级剔除，遗漏 `Transition` 的 `CanTransitionToSelf` 设置，未提供混合树的创建（Blend Tree）。",
      "github地址": "https://github.com/xiaoyu-li-china/test_dogfooding/tree/main/packages",
      "分支/文件夹": "master",
      "截图（产物/运行结果/对话）": "[图片]",
      "日志轨迹": "未提供详细日志轨迹，见截图"
    }
  ],
  "batch91": [
    {
      "Trae Session ID": "session_451",
      "轮次": "第一轮",
      "User Prompt": "使用 dbt (data build tool) 构建数据仓库模型，源表为订单、用户、产品，创建事实表（订单明细）和维度表（用户维度、产品维度），定义模型依赖关系。",
      "任务类型": "0-1代码生成",
      "业务领域": "数据分析与可视化",
      "修改范围": "模块内多文件",
      "任务是否完成": "未完成任务",
      "产物及过程是否满意": "不满意",
      "不满意原因": "产物不满意：未说明 dbt 的物化策略（`table` vs `view`），复现条件为大表时 view 查询慢，代码示例需配置 `materialized='incremental'`，未实现增量加载的 `is_incremental` 条件，遗漏测试（`dbt test`）的唯一性和非空约束，未提供文档生成（`dbt docs`）。",
      "github地址": "https://github.com/xiaoyu-li-china/test_dogfooding/tree/main/packages",
      "分支/文件夹": "master",
      "截图（产物/运行结果/对话）": "[图片]",
      "日志轨迹": "未提供详细日志轨迹，见截图"
    },
    {
      "Trae Session ID": "session_452",
      "轮次": "第二轮",
      "User Prompt": "修复增量模型重复加载数据（未处理更新），以及源表 schema 变更时模型失败。",
      "任务类型": "Bug修复",
      "业务领域": "数据分析与可视化",
      "修改范围": "模块内多文件",
      "任务是否完成": "未完成任务",
      "产物及过程是否满意": "不满意",
      "不满意原因": "产物不满意：未明确 `on_schema_change` 的配置（`append_new_columns`），复现条件为源表新增列，代码示例需设置 `on_schema_change='sync_all_columns'`，未实现删除列的警告，遗漏增量窗口的过滤（`where` 条件），未测试依赖模型的顺序执行。",
      "github地址": "https://github.com/xiaoyu-li-china/test_dogfooding/tree/main/packages",
      "分支/文件夹": "master",
      "截图（产物/运行结果/对话）": "[图片]",
      "日志轨迹": "未提供详细日志轨迹，见截图"
    },
    {
      "Trae Session ID": "session_453",
      "轮次": "第三轮",
      "User Prompt": "增加数据质量测试（自定义 SQL 测试），以及 dbt 与 Airflow 集成（调度执行）。",
      "任务类型": "Feature迭代",
      "业务领域": "数据分析与可视化",
      "修改范围": "模块内多文件",
      "任务是否完成": "未完成任务",
      "产物及过程是否满意": "不满意",
      "不满意原因": "产物不满意：未说明测试的粒度（单列 vs 多列组合），复现条件为复合主键测试，代码示例需提供 `dbt_utils` 宏，未实现 Airflow 的 dbt operator 配置，遗漏测试失败时的告警，未提供测试结果的可视化。",
      "github地址": "https://github.com/xiaoyu-li-china/test_dogfooding/tree/main/packages",
      "分支/文件夹": "master",
      "截图（产物/运行结果/对话）": "[图片]",
      "日志轨迹": "未提供详细日志轨迹，见截图"
    },
    {
      "Trae Session ID": "session_454",
      "轮次": "第四轮",
      "User Prompt": "编写 dbt 单元测试（`dbt test`），验证模型中的计算逻辑（如订单金额 = 数量 * 单价）。",
      "任务类型": "代码测试",
      "业务领域": "数据分析与可视化",
      "修改范围": "模块内多文件",
      "任务是否完成": "未完成任务",
      "产物及过程是否满意": "不满意",
      "不满意原因": "产物不满意：未说明 dbt 单元测试的种子数据（`seed` 文件），复现条件为依赖关联模型，代码示例需使用 `dbt seed` 和 `ref` 函数，未测试异常值（空值、负数），遗漏增量模型的历史重跑测试，未提供性能测试的 query plan。",
      "github地址": "https://github.com/xiaoyu-li-china/test_dogfooding/tree/main/packages",
      "分支/文件夹": "master",
      "截图（产物/运行结果/对话）": "[图片]",
      "日志轨迹": "未提供详细日志轨迹，见截图"
    },
    {
      "Trae Session ID": "session_455",
      "轮次": "第五轮",
      "User Prompt": "解释 dbt 的 Jinja 模板和宏，以及 `ref` 函数如何解析依赖。给出生成曲面表（SURFACE）的宏示例。",
      "任务类型": "代码理解",
      "业务领域": "数据分析与可视化",
      "修改范围": "代码理解文档",
      "任务是否完成": "未完成任务",
      "产物及过程是否满意": "不满意",
      "不满意原因": "产物不满意：未明确宏的上下文（`flags` 变量），复现条件为开发与生产环境不同，代码示例需使用 `target.name`，未解释 `config` 块的作用，遗漏 `source` 函数用于原始表，未提供 `run_query` 的动态列生成。",
      "github地址": "https://github.com/xiaoyu-li-china/test_dogfooding/tree/main/packages",
      "分支/文件夹": "master",
      "截图（产物/运行结果/对话）": "[图片]",
      "日志轨迹": "未提供详细日志轨迹，见截图"
    }
  ],
  "batch92": [
    {
      "Trae Session ID": "session_456",
      "轮次": "第一轮",
      "User Prompt": "使用 Three.js 实现体积光效果（从太阳方向射出），使用后处理（UnrealBloomPass）或自定义着色器，光线随相机移动而动态变化。",
      "任务类型": "0-1代码生成",
      "业务领域": "3D/交互可视化",
      "修改范围": "模块内多文件",
      "任务是否完成": "未完成任务",
      "产物及过程是否满意": "不满意",
      "不满意原因": "产物不满意：未说明体积光的实现方式（射线步进或屏幕空间），复现条件为性能开销大，代码示例需使用简单 Scattering 模型，未实现光线的颜色衰减，遗漏光源与相机角度的 Fresnel 效果，未提供体积光的强度调节。",
      "github地址": "https://github.com/xiaoyu-li-china/test_dogfooding/tree/main/packages",
      "分支/文件夹": "master",
      "截图（产物/运行结果/对话）": "[图片]",
      "日志轨迹": "未提供详细日志轨迹，见截图"
    },
    {
      "Trae Session ID": "session_457",
      "轮次": "第二轮",
      "User Prompt": "修复体积光在地形内部可见（深度测试错误），以及相机旋转时光线闪烁（采样噪声）。",
      "任务类型": "Bug修复",
      "业务领域": "3D/交互可视化",
      "修改范围": "模块内多文件",
      "任务是否完成": "未完成任务",
      "产物及过程是否满意": "不满意",
      "不满意原因": "产物不满意：未明确深度测试的修正（`depthTest: true`），复现条件为地形与光线重叠，代码示例需设置 `depthWrite: false`，未实现多帧累积的 jitter 消除，遗漏光线步进的步长自适应（距离），未测试体积光在雾效中的融合。",
      "github地址": "https://github.com/xiaoyu-li-china/test_dogfooding/tree/main/packages",
      "分支/文件夹": "master",
      "截图（产物/运行结果/对话）": "[图片]",
      "日志轨迹": "未提供详细日志轨迹，见截图"
    },
    {
      "Trae Session ID": "session_458",
      "轮次": "第三轮",
      "User Prompt": "增加体积光的运动（云层飘动），以及颜色随时间的渐变（日出日落）。",
      "任务类型": "Feature迭代",
      "业务领域": "3D/交互可视化",
      "修改范围": "模块内多文件",
      "任务是否完成": "未完成任务",
      "产物及过程是否满意": "不满意",
      "不满意原因": "产物不满意：未说明光线运动的插值（`Clock.getElapsedTime`），复现条件为速度变化不自然，代码示例需平滑曲线，未实现颜色与光线强度的 LDR 映射，遗漏体积光与阴影的联动，未提供光线的噪声纹理（云状）。",
      "github地址": "https://github.com/xiaoyu-li-china/test_dogfooding/tree/main/packages",
      "分支/文件夹": "master",
      "截图（产物/运行结果/对话）": "[图片]",
      "日志轨迹": "未提供详细日志轨迹，见截图"
    },
    {
      "Trae Session ID": "session_459",
      "轮次": "第四轮",
      "User Prompt": "编写单元测试测试光线步进的数学函数（给定起点方向，计算采样点），使用假数据。",
      "任务类型": "代码测试",
      "业务领域": "3D/交互可视化",
      "修改范围": "模块内多文件",
      "任务是否完成": "未完成任务",
      "产物及过程是否满意": "不满意",
      "不满意原因": "产物不满意：未说明测试中需要模拟场景深度（mock），复现条件为依赖真实渲染，代码示例使用公式计算，未测试散射积分的数值稳定性，遗漏体积光透明度与距离的衰减，未提供性能基准（步进次数 vs 质量）。",
      "github地址": "https://github.com/xiaoyu-li-china/test_dogfooding/tree/main/packages",
      "分支/文件夹": "master",
      "截图（产物/运行结果/对话）": "[图片]",
      "日志轨迹": "未提供详细日志轨迹，见截图"
    },
    {
      "Trae Session ID": "session_460",
      "轮次": "第五轮",
      "User Prompt": "解释体积光的物理模型（瑞利散射），以及屏幕空间实现的光线步进算法。给出片段着色器中步进积分代码。",
      "任务类型": "代码理解",
      "业务领域": "3D/交互可视化",
      "修改范围": "代码理解文档",
      "任务是否完成": "未完成任务",
      "产物及过程是否满意": "不满意",
      "不满意原因": "产物不满意：未明确步进次数的平衡（32 次较优），复现条件为步进太多性能下降，代码示例需可配置，未解释光照强度的指数衰减，遗漏 `pow` 函数的颜色校正，未提供环境遮蔽的近似。",
      "github地址": "https://github.com/xiaoyu-li-china/test_dogfooding/tree/main/packages",
      "分支/文件夹": "master",
      "截图（产物/运行结果/对话）": "[图片]",
      "日志轨迹": "未提供详细日志轨迹，见截图"
    }
  ]
}
