{
  "batch168": [
    {
      "Trae Session ID": "session_840",
      "轮次": "第一轮",
      "User Prompt": "在 Python 中编写脚本 dir_tree.py，递归遍历指定目录，生成目录树结构（类似 tree 命令），输出到文本文件 tree.txt。要求：忽略 .git、node_modules、__pycache__ 目录；每个层级用空格缩进；文件大小超过 1MB 的在文件名后标记 [large]。",
      "任务类型": "0-1代码生成",
      "业务领域": "命令行工具",
      "修改范围": "模块内多文件",
      "任务是否完成": "未完成任务",
      "产物及过程是否满意": "不满意",
      "不满意原因": "产物不满意：用了 os.walk 但递归打印时缩进乱了，没记录深度，所有文件都顶格写（与「格式美观目录树」需求不符，阻塞可读输出，复现：三层嵌套目录）。IGNORE 目录名大小写敏感，.Git 未跳过（边界场景，部分功能异常）。[large] 阈值 1MB 用 st_size 但未处理权限拒绝 stat 失败（边界漏测）。",
      "github地址": "https://github.com/xiaoyu-li-china/test_dogfooding/tree/main/packages",
      "分支/文件夹": "master",
      "截图（产物/运行结果/对话）": "[图片]",
      "日志轨迹": "未提供详细日志轨迹，见截图"
    },
    {
      "Trae Session ID": "session_841",
      "轮次": "第二轮",
      "User Prompt": "修复目录树生成脚本在处理符号链接时陷入无限循环的问题。遇到符号链接时，只显示链接名称和目标路径，不再继续遍历其内部。另外修复大文件标记只判断了 .ext 的大小，但没考虑文件夹大小。",
      "任务类型": "Bug修复",
      "业务领域": "命令行工具",
      "修改范围": "模块内多文件",
      "任务是否完成": "未完成任务",
      "产物及过程是否满意": "不满意",
      "不满意原因": "产物不满意：判断符号链接用了 os.path.islink 但忘了 os.readlink 获取目标路径，输出只有文件名没有 ->（与「link_name -> target」需求不符，复现：链到 ../other 的软链）。文件夹仍按聚合大小标 [large]，与「文件夹不标记」规则冲突（规则错误，部分功能异常）。循环检测仅靠 visited inode set，硬链接同 inode 误跳过（边界场景）。",
      "github地址": "https://github.com/xiaoyu-li-china/test_dogfooding/tree/main/packages",
      "分支/文件夹": "master",
      "截图（产物/运行结果/对话）": "[图片]",
      "日志轨迹": "未提供详细日志轨迹，见截图"
    },
    {
      "Trae Session ID": "session_842",
      "轮次": "第三轮",
      "User Prompt": "增加 --json 参数，将目录树输出为 JSON 格式（嵌套对象），每个节点包含 name、type（file/dir）、size（字节）、children（目录）。同时支持 --max-depth 限制遍历深度。",
      "任务类型": "Feature迭代",
      "业务领域": "命令行工具",
      "修改范围": "模块内多文件",
      "任务是否完成": "未完成任务",
      "产物及过程是否满意": "不满意",
      "不满意原因": "产物不满意：JSON 输出时没有处理文件名中的特殊字符如双引号，生成的 JSON 非法无法解析（阻塞 --json 主流程，复现：文件名含 \"report\"）。max-depth 对 symlink 仍 descend 导致深度计数不准（边界场景，部分功能异常）。size 对目录递归求和性能 O(n^2) 大目录卡顿（性能边界）。",
      "github地址": "https://github.com/xiaoyu-li-china/test_dogfooding/tree/main/packages",
      "分支/文件夹": "master",
      "截图（产物/运行结果/对话）": "[图片]",
      "日志轨迹": "未提供详细日志轨迹，见截图"
    },
    {
      "Trae Session ID": "session_843",
      "轮次": "第四轮",
      "User Prompt": "为目录树生成函数编写单元测试（pytest），使用 tempfile 创建临时目录结构，测试：1）忽略的目录不出现；2）大文件标记正确；3）--max-depth 生效。",
      "任务类型": "代码测试",
      "业务领域": "命令行工具",
      "修改范围": "模块内多文件",
      "任务是否完成": "未完成任务",
      "产物及过程是否满意": "不满意",
      "不满意原因": "产物不满意：测试创建了很多文件和目录，但没测试符号链接情况，tempfile 不支持创建软链就跳过了（与 Bug 修复轮未对齐，测试盲区，符号链接逻辑实际没覆盖）。ignore 列表未测 __pycache__ 嵌套（边界漏测）。JSON 非法字符 case 缺失（与第三轮未对齐）。",
      "github地址": "https://github.com/xiaoyu-li-china/test_dogfooding/tree/main/packages",
      "分支/文件夹": "master",
      "截图（产物/运行结果/对话）": "[图片]",
      "日志轨迹": "未提供详细日志轨迹，见截图"
    },
    {
      "Trae Session ID": "session_844",
      "轮次": "第五轮",
      "User Prompt": "解释 os.walk 与 scandir 的性能差异，为什么推荐使用 scandir 来遍历大目录。给出一个使用 scandir 重构目录树生成的代码片段。",
      "任务类型": "代码理解",
      "业务领域": "命令行工具",
      "修改范围": "代码理解文档",
      "任务是否完成": "未完成任务",
      "产物及过程是否满意": "不满意",
      "不满意原因": "产物不满意：scandir 例子中目录递归又调用了 os.listdir，混用 API 没有完全用 scandir 实现递归（示例错误，与推荐做法矛盾，维护误导）。未量化 stat 调用次数差异（解释不够深入）。未提及 DirEntry.is_symlink() 避免 extra stat（扩展缺口）。",
      "github地址": "https://github.com/xiaoyu-li-china/test_dogfooding/tree/main/packages",
      "分支/文件夹": "master",
      "截图（产物/运行结果/对话）": "[图片]",
      "日志轨迹": "未提供详细日志轨迹，见截图"
    }
  ],
  "batch169": [
    {
      "Trae Session ID": "session_845",
      "轮次": "第一轮",
      "User Prompt": "在 Spring Boot 项目中实现一个“防止重复提交”的注解 @NoRepeatSubmit，基于 Redis 和 AOP。对加了注解的 POST 接口，同一用户同一接口在 3 秒内重复请求返回 409。Key 为 用户ID + 请求路径 + 请求参数 MD5。",
      "任务类型": "0-1代码生成",
      "业务领域": "纯后端 API 服务",
      "修改范围": "模块内多文件",
      "任务是否完成": "未完成任务",
      "产物及过程是否满意": "不满意",
      "不满意原因": "产物不满意：生成 MD5 时把整个请求体 toString()，JSON 字段顺序不同导致 MD5 不同，同一请求体因字段顺序变就被当成不同请求（核心逻辑错误，防重复失效，复现：Jackson 序列化 key 顺序变化）。AOP 未捕获 multipart 参数（边界场景，部分功能异常）。409 响应体无统一错误码（体验问题）。",
      "github地址": "https://github.com/xiaoyu-li-china/test_dogfooding/tree/main/packages",
      "分支/文件夹": "master",
      "截图（产物/运行结果/对话）": "[图片]",
      "日志轨迹": "未提供详细日志轨迹，见截图"
    },
    {
      "Trae Session ID": "session_846",
      "轮次": "第二轮",
      "User Prompt": "修复重复提交锁在分布式环境下失效的问题（多实例部署时各实例自己 Redis 锁独立）。要求使用 Redis 分布式锁（Redisson）或 Lua 脚本保证原子性。同时修复用户切换账号后锁未释放的问题。",
      "任务类型": "Bug修复",
      "业务领域": "纯后端 API 服务",
      "修改范围": "模块内多文件",
      "任务是否完成": "未完成任务",
      "产物及过程是否满意": "不满意",
      "不满意原因": "产物不满意：用了 Redisson RLock 但解锁时忘了校验当前线程是否持有锁，其他请求也能 unlock 导致锁失效（安全边界，严重，复现：线程 A 持锁线程 B unlock）。用户切换账号后 key 仍含旧 userId 未清 session 关联（边界场景，部分功能异常）。Lua 脚本未设置 lock 过期与业务耗时匹配（运维边界）。",
      "github地址": "https://github.com/xiaoyu-li-china/test_dogfooding/tree/main/packages",
      "分支/文件夹": "master",
      "截图（产物/运行结果/对话）": "[图片]",
      "日志轨迹": "未提供详细日志轨迹，见截图"
    },
    {
      "Trae Session ID": "session_847",
      "轮次": "第三轮",
      "User Prompt": "增加“幂等性 Token”机制，客户端先请求获取 Token（存入 Redis），提交时携带 Token，服务端验证后删除 Token（一次性）。要求 Token 有效期 5 分钟。同时兼容旧的防重复提交注解（两者可并存）。",
      "任务类型": "Feature迭代",
      "业务领域": "纯后端 API 服务",
      "修改范围": "模块内多文件",
      "任务是否完成": "未完成任务",
      "产物及过程是否满意": "不满意",
      "不满意原因": "产物不满意：获取 Token 接口没有做限流，恶意用户可刷大量 Token 占用 Redis 内存（安全边界，资源 DoS）。Token 验证和业务操作没有放在同一事务中，验证成功后业务失败 Token 已删用户无法重试（核心流程错误，阻塞重试）。旧注解与新 Token 优先级未文档（维护风险）。",
      "github地址": "https://github.com/xiaoyu-li-china/test_dogfooding/tree/main/packages",
      "分支/文件夹": "master",
      "截图（产物/运行结果/对话）": "[图片]",
      "日志轨迹": "未提供详细日志轨迹，见截图"
    },
    {
      "Trae Session ID": "session_848",
      "轮次": "第四轮",
      "User Prompt": "为 @NoRepeatSubmit 注解编写集成测试（Spring Boot Test + MockMvc）。测试场景：正常请求成功；1 秒内重复请求返回 409；不同用户之间不互相影响。",
      "任务类型": "代码测试",
      "业务领域": "纯后端 API 服务",
      "修改范围": "模块内多文件",
      "任务是否完成": "未完成任务",
      "产物及过程是否满意": "不满意",
      "不满意原因": "产物不满意：测试用 CountDownLatch 模拟并发，但 Redis key 过期 3 秒，测试跑得慢时锁自动过期导致断言失败（测试不稳定，与并发场景未对齐）。未测 Token 机制并存路径（第三轮需求未对齐，测试盲区）。MockMvc 未带不同 Authorization header 验用户隔离（边界漏测）。",
      "github地址": "https://github.com/xiaoyu-li-china/test_dogfooding/tree/main/packages",
      "分支/文件夹": "master",
      "截图（产物/运行结果/对话）": "[图片]",
      "日志轨迹": "未提供详细日志轨迹，见截图"
    },
    {
      "Trae Session ID": "session_849",
      "轮次": "第五轮",
      "User Prompt": "解释分布式锁在防重复提交中的局限性（锁超时、GC 停顿导致的误判），以及 Redlock 算法的争议。给出基于数据库唯一索引的替代方案。",
      "任务类型": "代码理解",
      "业务领域": "纯后端 API 服务",
      "修改范围": "代码理解文档",
      "任务是否完成": "未完成任务",
      "产物及过程是否满意": "不满意",
      "不满意原因": "产物不满意：说数据库唯一索引无法应对高并发但没解释为什么，插入冲突时间隙锁导致性能下降（解释太笼统，维护误导）。未提 fencing token 解决 GC 停顿（扩展缺口）。Redlock 争议未引用 Martin Kleppmann 观点（解释深度不足）。",
      "github地址": "https://github.com/xiaoyu-li-china/test_dogfooding/tree/main/packages",
      "分支/文件夹": "master",
      "截图（产物/运行结果/对话）": "[图片]",
      "日志轨迹": "未提供详细日志轨迹，见截图"
    }
  ],
  "batch170": [
    {
      "Trae Session ID": "session_850",
      "轮次": "第一轮",
      "User Prompt": "在 React Native 中实现一个“启动闪屏页”（Splash Screen），应用启动时先显示自定义的图片 2 秒，然后自动跳转到首页。要求支持 Android 和 iOS，图片资源本地打包。",
      "任务类型": "0-1代码生成",
      "业务领域": "移动端",
      "修改范围": "模块内多文件",
      "任务是否完成": "未完成任务",
      "产物及过程是否满意": "不满意",
      "不满意原因": "产物不满意：Android 冷启动时 Splash 显示后黑了半秒再进首页，因为在 useEffect 里 setTimeout 延迟跳转，React 组件渲染有间隙导致黑屏（与「2 秒后进入主页」需求不符，复现：Android 冷启动）。未使用 react-native-splash-screen 原生层控制隐藏时机（架构缺陷，阻塞体验）。iOS LaunchScreen 与 JS Splash 双屏闪烁（体验问题）。",
      "github地址": "https://github.com/xiaoyu-li-china/test_dogfooding/tree/main/packages",
      "分支/文件夹": "master",
      "截图（产物/运行结果/对话）": "[图片]",
      "日志轨迹": "未提供详细日志轨迹，见截图"
    },
    {
      "Trae Session ID": "session_851",
      "轮次": "第二轮",
      "User Prompt": "修复 Android 设备上旋转屏幕时 Splash 图片被拉伸的问题。要求图片保持比例，居中显示，背景色填充。同时修复 iOS 上 Splash 显示期间用户点击屏幕会跳过的问题（应该禁止点击）。",
      "任务类型": "Bug修复",
      "业务领域": "移动端",
      "修改范围": "模块内多文件",
      "任务是否完成": "未完成任务",
      "产物及过程是否满意": "不满意",
      "不满意原因": "产物不满意：禁止点击用了 pointerEvents: 'none'，但 iOS Native 层仍然响应点击会跳过 Splash（平台差异，与「点击无反应」需求不符，需原生模块禁用交互）。Android resizeMode 用 stretch 未改 cover（部分功能异常，旋转仍变形）。未监听 Dimensions 变化重算布局（边界场景）。",
      "github地址": "https://github.com/xiaoyu-li-china/test_dogfooding/tree/main/packages",
      "分支/文件夹": "master",
      "截图（产物/运行结果/对话）": "[图片]",
      "日志轨迹": "未提供详细日志轨迹，见截图"
    },
    {
      "Trae Session ID": "session_852",
      "轮次": "第三轮",
      "User Prompt": "为 Splash 增加“加载进度”功能，在图片下方显示进度条（模拟资源加载）。进度条从 0% 到 100%，2 秒内匀速增长。同时支持通过网络获取远程配置后再跳转（--remote-config）。",
      "任务类型": "Feature迭代",
      "业务领域": "移动端",
      "修改范围": "模块内多文件",
      "任务是否完成": "未完成任务",
      "产物及过程是否满意": "不满意",
      "不满意原因": "产物不满意：用 setInterval 模拟进度，但远程配置请求可能提前完成，进度条还没到 100% 就跳转看起来很奇怪（与「根据实际加载进度更新」需求偏差，体验问题）。remote-config 失败无 fallback 停留白屏（阻塞主流程，部分功能异常）。进度条与跳转未用 Promise.all 协调（逻辑错误）。",
      "github地址": "https://github.com/xiaoyu-li-china/test_dogfooding/tree/main/packages",
      "分支/文件夹": "master",
      "截图（产物/运行结果/对话）": "[图片]",
      "日志轨迹": "未提供详细日志轨迹，见截图"
    },
    {
      "Trae Session ID": "session_853",
      "轮次": "第四轮",
      "User Prompt": "为 Splash 组件编写单元测试（React Native Testing Library），测试：1）初始时显示 Splash；2）2 秒后跳转；3）模拟远程配置延迟，验证跳转时机。",
      "任务类型": "代码测试",
      "业务领域": "移动端",
      "修改范围": "模块内多文件",
      "任务是否完成": "未完成任务",
      "产物及过程是否满意": "不满意",
      "不满意原因": "产物不满意：act 中推进时间后断言跳转函数被调用，但 NavigationContainer 的 navigate 没有被 mock，测试运行时真实跳转失败（测试无效，与跳转验证需求未对齐）。fake timer 未 advance 远程 config delay 分支（边界漏测）。未测 Android 黑屏时序（平台边界跳过但无文档说明）。",
      "github地址": "https://github.com/xiaoyu-li-china/test_dogfooding/tree/main/packages",
      "分支/文件夹": "master",
      "截图（产物/运行结果/对话）": "[图片]",
      "日志轨迹": "未提供详细日志轨迹，见截图"
    },
    {
      "Trae Session ID": "session_854",
      "轮次": "第五轮",
      "User Prompt": "解释 React Native 中 Native 模块（SplashScreen）与 JS 层的交互原理，以及冷启动时白屏的原因和解决方案（new NativeEventEmitter + AppRegistry）。给出一个自定义原生模块控制 Splash 隐藏的代码。",
      "任务类型": "代码理解",
      "业务领域": "移动端",
      "修改范围": "代码理解文档",
      "任务是否完成": "未完成任务",
      "产物及过程是否满意": "不满意",
      "不满意原因": "产物不满意：说自定义原生模块需要在 ReactApplication 中注册，但漏掉 ReactPackage 的添加步骤，代码不完整（文档错误，对接阻塞）。未说明 MainActivity onCreate 中 SplashTheme 切换时机（边界场景遗漏）。AppRegistry 回调与原生 hide 时序未画序列图（解释不完整）。",
      "github地址": "https://github.com/xiaoyu-li-china/test_dogfooding/tree/main/packages",
      "分支/文件夹": "master",
      "截图（产物/运行结果/对话）": "[图片]",
      "日志轨迹": "未提供详细日志轨迹，见截图"
    }
  ],
  "batch171": [
    {
      "Trae Session ID": "session_855",
      "轮次": "第一轮",
      "User Prompt": "在 Express + MongoDB 中实现“邮件激活账号”功能。用户注册后发送激活邮件（包含激活链接，带 token），点击链接后验证 token，激活账号。要求 token 有效期 24 小时，使用 jsonwebtoken 签名，用户表有 isActive 字段。",
      "任务类型": "0-1代码生成",
      "业务领域": "纯后端 API 服务",
      "修改范围": "模块内多文件",
      "任务是否完成": "未完成任务",
      "产物及过程是否满意": "不满意",
      "不满意原因": "产物不满意：激活链接里 token 用了 JWT，但验证时没有检查 exp 字段，过期 token 也能激活账号（安全边界，严重，与「24 小时有效期」需求严重冲突，复现：签发 25h 前 token 仍 200）。isActive 默认 true 未改，注册即可登录（核心流程错误）。邮件链接 base URL 写死 localhost（环境阻塞）。",
      "github地址": "https://github.com/xiaoyu-li-china/test_dogfooding/tree/main/packages",
      "分支/文件夹": "master",
      "截图（产物/运行结果/对话）": "[图片]",
      "日志轨迹": "未提供详细日志轨迹，见截图"
    },
    {
      "Trae Session ID": "session_856",
      "轮次": "第二轮",
      "User Prompt": "修复邮件发送失败时用户注册成功但没收到激活邮件的问题。要求使用消息队列（Bull）异步重试发送，最多 3 次，失败后记录日志并标记用户为“待激活”状态，管理员后台可手动重发。",
      "任务类型": "Bug修复",
      "业务领域": "纯后端 API 服务",
      "修改范围": "模块内多文件",
      "任务是否完成": "未完成任务",
      "产物及过程是否满意": "不满意",
      "不满意原因": "产物不满意：用了 Bull 队列但没有处理 Redis 连接断开的情况，队列任务丢失重试也没用（运维边界，阻塞可靠投递，复现：Redis restart 期间注册）。失败 3 次后用户状态 pending_activation 未暴露给管理端 API（部分功能异常）。sendMail 错误未分类 transient/permanent（重试策略错误）。",
      "github地址": "https://github.com/xiaoyu-li-china/test_dogfooding/tree/main/packages",
      "分支/文件夹": "master",
      "截图（产物/运行结果/对话）": "[图片]",
      "日志轨迹": "未提供详细日志轨迹，见截图"
    },
    {
      "Trae Session ID": "session_857",
      "轮次": "第三轮",
      "User Prompt": "增加“重新发送激活邮件”接口，限制同一用户 5 分钟内只能请求一次。新 token 应使旧 token 失效，防止旧链接继续激活。",
      "任务类型": "Feature迭代",
      "业务领域": "纯后端 API 服务",
      "修改范围": "模块内多文件",
      "任务是否完成": "未完成任务",
      "产物及过程是否满意": "不满意",
      "不满意原因": "产物不满意：让旧 token 失效的方式是在用户表存 activationTokenVersion，但 JWT 无状态，验证时忘了检查版本号，旧 token 仍然可用（核心安全错误，与「旧链接失效」需求不符，复现：重发后用旧链接仍可激活）。5 分钟限流仅内存 Map，多实例不共享（分布式边界，部分功能异常）。重发未 rotate secret（维护风险）。",
      "github地址": "https://github.com/xiaoyu-li-china/test_dogfooding/tree/main/packages",
      "分支/文件夹": "master",
      "截图（产物/运行结果/对话）": "[图片]",
      "日志轨迹": "未提供详细日志轨迹，见截图"
    },
    {
      "Trae Session ID": "session_858",
      "轮次": "第四轮",
      "User Prompt": "为激活流程编写集成测试，使用 MongoDB 内存数据库和 nodemailer 的测试帐号。测试：注册成功发送邮件；激活链接正确；重复激活返回 400。",
      "任务类型": "代码测试",
      "业务领域": "纯后端 API 服务",
      "修改范围": "模块内多文件",
      "任务是否完成": "未完成任务",
      "产物及过程是否满意": "不满意",
      "不满意原因": "产物不满意：测试 mock nodemailer 时只 mock 了 sendMail 方法，没模拟 transporter 的创建，测试跑起来还是连了真实 SMTP（测试无效，CI 可能连外网失败）。重复激活 400 未测过期 token（边界漏测）。JWT version 失效路径无覆盖（与第三轮未对齐）。",
      "github地址": "https://github.com/xiaoyu-li-china/test_dogfooding/tree/main/packages",
      "分支/文件夹": "master",
      "截图（产物/运行结果/对话）": "[图片]",
      "日志轨迹": "未提供详细日志轨迹，见截图"
    },
    {
      "Trae Session ID": "session_859",
      "轮次": "第五轮",
      "User Prompt": "解释 JWT 作为激活 token 的优缺点，相比随机字符串存储到数据库有什么优劣？说明为什么 JWT 可以免存储但无法撤销单个 token。",
      "任务类型": "代码理解",
      "业务领域": "纯后端 API 服务",
      "修改范围": "代码理解文档",
      "任务是否完成": "未完成任务",
      "产物及过程是否满意": "不满意",
      "不满意原因": "产物不满意：说 Redis 黑名单会引入额外存储，但忘了提黑名单过期时间可设成和 token 有效期一致避免无限增长（解释不完整，运维误导）。未对比 activation token 用 opaque id + DB 的一行方案（扩展缺口）。未说明 JWT 泄露后无法单点撤销的业务风险（边界场景）。",
      "github地址": "https://github.com/xiaoyu-li-china/test_dogfooding/tree/main/packages",
      "分支/文件夹": "master",
      "截图（产物/运行结果/对话）": "[图片]",
      "日志轨迹": "未提供详细日志轨迹，见截图"
    }
  ]
}
