{
  "batch189": [
    {
      "Trae Session ID": "session_941",
      "轮次": "第一轮",
      "User Prompt": "在 MongoDB 中有一个 orders 集合，字段：userId, amount, createdAt。写一个聚合查询，统计每个用户的总订单金额、平均订单金额、订单数量，按总金额降序排序。",
      "任务类型": "0-1代码生成",
      "业务领域": "纯后端 API 服务",
      "修改范围": "模块内多文件",
      "任务是否完成": "未完成任务",
      "产物及过程是否满意": "不满意",
      "不满意原因": "产物不满意：使用 $group 和 $sum，但未处理没有订单的用户，结果中不包含这些用户，业务上可能需要显示 0（与每个用户统计指标需求偏差，复现：users 100 人 orders 仅 80 人）。amount null 未 $ifNull 导致 sum 异常（数据错误）。未建 userId 索引提示（性能边界）。",
      "github地址": "https://github.com/xiaoyu-li-china/test_dogfooding/tree/main/packages",
      "分支/文件夹": "master",
      "截图（产物/运行结果/对话）": "[图片]",
      "日志轨迹": "未提供详细日志轨迹，见截图"
    },
    {
      "Trae Session ID": "session_942",
      "轮次": "第二轮",
      "User Prompt": "修复聚合查询中日期范围过滤（查询上个月数据）的时区问题，createdAt 存储 UTC 时间，需要转换为本地时区。要求支持通过参数传入时区偏移。",
      "任务类型": "Bug修复",
      "业务领域": "纯后端 API 服务",
      "修改范围": "模块内多文件",
      "任务是否完成": "未完成任务",
      "产物及过程是否满意": "不满意",
      "不满意原因": "产物不满意：在聚合管道中使用 $add 调整时区，但未处理夏令时，且 $add 只能加固定毫秒数，无法处理时区名称如 Asia/Shanghai，不够准确（与本地时区一天开始/结束计算需求不符，复现：DST 切换边界 off 1h）。参数 offset 未校验范围（边界场景）。$match 未用 ISODate 边界（逻辑错误）。",
      "github地址": "https://github.com/xiaoyu-li-china/test_dogfooding/tree/main/packages",
      "分支/文件夹": "master",
      "截图（产物/运行结果/对话）": "[图片]",
      "日志轨迹": "未提供详细日志轨迹，见截图"
    },
    {
      "Trae Session ID": "session_943",
      "轮次": "第三轮",
      "User Prompt": "在聚合结果中增加“排名”字段（按总金额），并筛选出排名前 10 的用户。同时使用 $facet 分别统计总额和平均额。",
      "任务类型": "Feature迭代",
      "业务领域": "纯后端 API 服务",
      "修改范围": "模块内多文件",
      "任务是否完成": "未完成任务",
      "产物及过程是否满意": "不满意",
      "不满意原因": "产物不满意：使用 $facet 但两个子管道分别扫描全表，性能较差，应先 $group 再 $facet 复用结果（与返回前 10 名和整体统计需求性能不符，复现：百万 orders 全表扫两次）。$setWindowFields 排名未用索引（性能边界）。top10 与 totals facet 口径不一致（数据错误）。",
      "github地址": "https://github.com/xiaoyu-li-china/test_dogfooding/tree/main/packages",
      "分支/文件夹": "master",
      "截图（产物/运行结果/对话）": "[图片]",
      "日志轨迹": "未提供详细日志轨迹，见截图"
    },
    {
      "Trae Session ID": "session_944",
      "轮次": "第四轮",
      "User Prompt": "为聚合查询编写单元测试（使用 MongoDB 内存数据库），插入测试数据，断言查询结果。",
      "任务类型": "代码测试",
      "业务领域": "纯后端 API 服务",
      "修改范围": "模块内多文件",
      "任务是否完成": "未完成任务",
      "产物及过程是否满意": "不满意",
      "不满意原因": "产物不满意：内存数据库不支持某些聚合操作符如 $facet，导致测试执行失败（测试环境耦合，与不依赖真实 MongoDB 需求冲突，CI 阻塞）。时区 DST case 缺失（与 Bug 轮未对齐）。空用户 0 订单 case 未测（与 0-1 轮未对齐）。",
      "github地址": "https://github.com/xiaoyu-li-china/test_dogfooding/tree/main/packages",
      "分支/文件夹": "master",
      "截图（产物/运行结果/对话）": "[图片]",
      "日志轨迹": "未提供详细日志轨迹，见截图"
    },
    {
      "Trae Session ID": "session_945",
      "轮次": "第五轮",
      "User Prompt": "解释 MongoDB 聚合管道中的 $lookup 与 SQL 中 JOIN 的区别，以及性能注意事项（索引、分片）。给出一个 $lookup 的示例。",
      "任务类型": "代码理解",
      "业务领域": "纯后端 API 服务",
      "修改范围": "代码理解文档",
      "任务是否完成": "未完成任务",
      "产物及过程是否满意": "不满意",
      "不满意原因": "产物不满意：指出 $lookup 不支持 OR 条件，但 MongoDB 5.0 开始支持 let 和 pipeline 实现复杂关联，未提及此演进（文档过时，维护误导，遗漏新特性）。未提 $lookup 应配合 localField 索引（性能边界）。分片 $lookup 跨 shard 开销未说明（扩展缺口）。",
      "github地址": "https://github.com/xiaoyu-li-china/test_dogfooding/tree/main/packages",
      "分支/文件夹": "master",
      "截图（产物/运行结果/对话）": "[图片]",
      "日志轨迹": "未提供详细日志轨迹，见截图"
    }
  ],
  "batch190": [
    {
      "Trae Session ID": "session_946",
      "轮次": "第一轮",
      "User Prompt": "在 React 项目中使用 Zustand 创建一个计数器 store，包含 count 状态和 increment、decrement 动作。在组件中展示并使用。",
      "任务类型": "0-1代码生成",
      "业务领域": "Web前端",
      "修改范围": "模块内多文件",
      "任务是否完成": "未完成任务",
      "产物及过程是否满意": "不满意",
      "不满意原因": "产物不满意：组件中直接解构 const { count } = useStore()，导致每次任何状态变化都重新渲染，应使用 selector useStore(state => state.count) 优化（性能问题，与最佳实践不符，复现：大 store 无关字段更新也 rerender）。store 未 TypeScript 类型导出（维护边界）。actions 引用不稳定（边界场景）。",
      "github地址": "https://github.com/xiaoyu-li-china/test_dogfooding/tree/main/packages",
      "分支/文件夹": "master",
      "截图（产物/运行结果/对话）": "[图片]",
      "日志轨迹": "未提供详细日志轨迹，见截图"
    },
    {
      "Trae Session ID": "session_947",
      "轮次": "第二轮",
      "User Prompt": "修复 Zustand store 中异步 action 更新状态后组件未刷新（没有正确调用 set）。使用 set 合并状态，并处理异步错误。",
      "任务类型": "Bug修复",
      "业务领域": "Web前端",
      "修改范围": "模块内多文件",
      "任务是否完成": "未完成任务",
      "产物及过程是否满意": "不满意",
      "不满意原因": "产物不满意：异步 action 中 catch 部分未调用 set({ error })，用户看不到错误提示（与处理异步错误需求不符，复现：fetch 500 后 UI 无反馈）。set 直接替换 nested 对象未 spread（浅合并陷阱，部分功能异常）。loading 态未 finally clear（边界场景）。",
      "github地址": "https://github.com/xiaoyu-li-china/test_dogfooding/tree/main/packages",
      "分支/文件夹": "master",
      "截图（产物/运行结果/对话）": "[图片]",
      "日志轨迹": "未提供详细日志轨迹，见截图"
    },
    {
      "Trae Session ID": "session_948",
      "轮次": "第三轮",
      "User Prompt": "增加持久化中间件 persist，将 store 数据同步到 localStorage，刷新后恢复。同时增加 devtools 支持 Redux DevTools。",
      "任务类型": "Feature迭代",
      "业务领域": "Web前端",
      "修改范围": "模块内多文件",
      "任务是否完成": "未完成任务",
      "产物及过程是否满意": "不满意",
      "不满意原因": "产物不满意：使用 persist 但未配置 partialize，导致整个 store（包括函数）被序列化，触发报错（与刷新后 count 不变需求冲突，复现：persist 后白屏 JSON.stringify function）。devtools 与 persist 顺序错导致 action 名丢失（调试边界）。storage 版本 migrate 未配（升级边界）。",
      "github地址": "https://github.com/xiaoyu-li-china/test_dogfooding/tree/main/packages",
      "分支/文件夹": "master",
      "截图（产物/运行结果/对话）": "[图片]",
      "日志轨迹": "未提供详细日志轨迹，见截图"
    },
    {
      "Trae Session ID": "session_949",
      "轮次": "第四轮",
      "User Prompt": "为 Zustand store 编写单元测试（Jest），测试 increment、decrement 以及异步 action。",
      "任务类型": "代码测试",
      "业务领域": "Web前端",
      "修改范围": "模块内多文件",
      "任务是否完成": "未完成任务",
      "产物及过程是否满意": "不满意",
      "不满意原因": "产物不满意：异步 action 测试中直接调用 action 函数，未用 act 等待更新，断言时状态仍为旧值（测试无效，与异步获取后页面更新未对齐）。persist hydrate mock 缺失（第三轮未对齐）。selector 相等性未测（与 0-1 轮未对齐）。",
      "github地址": "https://github.com/xiaoyu-li-china/test_dogfooding/tree/main/packages",
      "分支/文件夹": "master",
      "截图（产物/运行结果/对话）": "[图片]",
      "日志轨迹": "未提供详细日志轨迹，见截图"
    },
    {
      "Trae Session ID": "session_950",
      "轮次": "第五轮",
      "User Prompt": "解释 Zustand 与 Redux 的核心差异（中间件、样板代码、性能优化）。说明 Zustand 中 set 函数合并状态的规则（浅合并）。",
      "任务类型": "代码理解",
      "业务领域": "Web前端",
      "修改范围": "代码理解文档",
      "任务是否完成": "未完成任务",
      "产物及过程是否满意": "不满意",
      "不满意原因": "产物不满意：指出 set 是浅合并，嵌套对象需手动展开，但未给出具体示例如 set({ user: { ...state.user, name } })（解释不完整，易误解，维护风险）。未对比 Redux Toolkit createSlice immer（扩展缺口）。subscribeWithSelector 未提（最佳实践遗漏）。",
      "github地址": "https://github.com/xiaoyu-li-china/test_dogfooding/tree/main/packages",
      "分支/文件夹": "master",
      "截图（产物/运行结果/对话）": "[图片]",
      "日志轨迹": "未提供详细日志轨迹，见截图"
    }
  ],
  "batch191": [
    {
      "Trae Session ID": "session_951",
      "轮次": "第一轮",
      "User Prompt": "在 Vue Router 4 中实现全局前置守卫，检查用户是否登录（store 中的 token）。未登录访问需要认证的页面（meta: { requiresAuth: true }）时跳转到 /login，并保存目标路径。",
      "任务类型": "0-1代码生成",
      "业务领域": "Web前端",
      "修改范围": "模块内多文件",
      "任务是否完成": "未完成任务",
      "产物及过程是否满意": "不满意",
      "不满意原因": "产物不满意：目标路径保存在 localStorage，登录成功后未清除，导致下次登录仍跳回旧页面（与登录后返回原页面需求冲突，复现：登出再登仍跳上次 deep link）。redirect query 与 localStorage 双写不一致（边界场景，部分功能异常）。requiresAuth 未处理嵌套路由 meta 继承（逻辑缺口）。",
      "github地址": "https://github.com/xiaoyu-li-china/test_dogfooding/tree/main/packages",
      "分支/文件夹": "master",
      "截图（产物/运行结果/对话）": "[图片]",
      "日志轨迹": "未提供详细日志轨迹，见截图"
    },
    {
      "Trae Session ID": "session_952",
      "轮次": "第二轮",
      "User Prompt": "修复守卫中异步检查 token 有效性的问题，例如 token 过期。调用后端接口验证，若无效则清除本地存储并跳转登录。",
      "任务类型": "Bug修复",
      "业务领域": "Web前端",
      "修改范围": "模块内多文件",
      "任务是否完成": "未完成任务",
      "产物及过程是否满意": "不满意",
      "不满意原因": "产物不满意：调用后端验证接口为同步等待，守卫阻塞路由跳转，用户体验差，应允许先进入页面再重定向或显示 loading（与过期 token 识别体验需求偏差，复现：慢网验证 3s 白屏）。验证失败未 clear refresh token（安全边界）。401 与 403 未区分（逻辑错误）。",
      "github地址": "https://github.com/xiaoyu-li-china/test_dogfooding/tree/main/packages",
      "分支/文件夹": "master",
      "截图（产物/运行结果/对话）": "[图片]",
      "日志轨迹": "未提供详细日志轨迹，见截图"
    },
    {
      "Trae Session ID": "session_953",
      "轮次": "第三轮",
      "User Prompt": "增加角色权限守卫，从 store 获取用户角色，根据 meta: { roles: ['admin'] } 判断是否允许访问，无权限时跳转 /403。",
      "任务类型": "Feature迭代",
      "业务领域": "Web前端",
      "修改范围": "模块内多文件",
      "任务是否完成": "未完成任务",
      "产物及过程是否满意": "不满意",
      "不满意原因": "产物不满意：仅检查角色是否匹配，未处理动态权限列表，无法支持细粒度控制（与角色鉴权扩展需求不符，复现：admin 子模块 read-only 仍放行）。403 页无返回入口（体验问题）。roles meta 字符串与数组混用未 normalize（边界场景）。",
      "github地址": "https://github.com/xiaoyu-li-china/test_dogfooding/tree/main/packages",
      "分支/文件夹": "master",
      "截图（产物/运行结果/对话）": "[图片]",
      "日志轨迹": "未提供详细日志轨迹，见截图"
    },
    {
      "Trae Session ID": "session_954",
      "轮次": "第四轮",
      "User Prompt": "为路由守卫编写单元测试（Vue Test Utils + Vue Router），模拟 store 状态，测试未登录跳转、角色鉴权。",
      "任务类型": "代码测试",
      "业务领域": "Web前端",
      "修改范围": "模块内多文件",
      "任务是否完成": "未完成任务",
      "产物及过程是否满意": "不满意",
      "不满意原因": "产物不满意：mock useRouter 后，守卫中使用的 next 函数被调用但未触发真实路由跳转，仅断言 next 的参数，测试不够真实（测试与导航行为未对齐，测试盲区）。异步 token 验证未 flush（与 Bug 轮未对齐）。动态 permissions case 缺失（第三轮未对齐）。",
      "github地址": "https://github.com/xiaoyu-li-china/test_dogfooding/tree/main/packages",
      "分支/文件夹": "master",
      "截图（产物/运行结果/对话）": "[图片]",
      "日志轨迹": "未提供详细日志轨迹，见截图"
    },
    {
      "Trae Session ID": "session_955",
      "轮次": "第五轮",
      "User Prompt": "解释 Vue Router 中 beforeEach、beforeResolve、afterEach 的执行时机差异。说明 next 函数多次调用的问题（死循环）。",
      "任务类型": "代码理解",
      "业务领域": "Web前端",
      "修改范围": "代码理解文档",
      "任务是否完成": "未完成任务",
      "产物及过程是否满意": "不满意",
      "不满意原因": "产物不满意：指出 next 多次调用可能导致死循环，但未给出示例，如调用 next(to) 后又被同一守卫拦截形成循环（解释不够具体，维护误导，边界场景遗漏）。未说明 beforeResolve 等 async 组件加载完成（扩展缺口）。next(false) 取消导航未提（解释深度不足）。",
      "github地址": "https://github.com/xiaoyu-li-china/test_dogfooding/tree/main/packages",
      "分支/文件夹": "master",
      "截图（产物/运行结果/对话）": "[图片]",
      "日志轨迹": "未提供详细日志轨迹，见截图"
    }
  ],
  "batch192": [
    {
      "Trae Session ID": "session_956",
      "轮次": "第一轮",
      "User Prompt": "写一个 Python 多进程池示例，计算 [i*i for i in range(10000000)] 的总和，使用 multiprocessing.Pool 的 map 分块计算，比较单进程和多进程耗时。",
      "任务类型": "0-1代码生成",
      "业务领域": "命令行工具",
      "修改范围": "模块内多文件",
      "任务是否完成": "未完成任务",
      "产物及过程是否满意": "不满意",
      "不满意原因": "产物不满意：分为 8 个进程，但任务过于简单，进程间通信开销大于计算收益，结果反而比单进程慢（与多进程更快预期不符，复现：简单 square 任务多进程更慢）。未 if __name__ guard 在示例片段中（Windows 边界）。chunk 划分未调优（性能误导）。",
      "github地址": "https://github.com/xiaoyu-li-china/test_dogfooding/tree/main/packages",
      "分支/文件夹": "master",
      "截图（产物/运行结果/对话）": "[图片]",
      "日志轨迹": "未提供详细日志轨迹，见截图"
    },
    {
      "Trae Session ID": "session_957",
      "轮次": "第二轮",
      "User Prompt": "修复多进程池在 Windows 上因 if __name__ == \"__main__\" 缺失导致无限递归的问题。同时增加进度条显示（tqdm）。",
      "任务类型": "Bug修复",
      "业务领域": "命令行工具",
      "修改范围": "模块内多文件",
      "任务是否完成": "未完成任务",
      "产物及过程是否满意": "不满意",
      "不满意原因": "产物不满意：添加 tqdm 但多进程池中更新进度条不共享，每个进程独立显示，导致进度条混乱（与有进度条需求不符，复现：8 个 tqdm bar 同时刷）。应使用 manager Queue 或 tqdm.contrib.logging（实现缺陷，体验问题）。__main__ guard 加在错误模块（部分功能异常）。",
      "github地址": "https://github.com/xiaoyu-li-china/test_dogfooding/tree/main/packages",
      "分支/文件夹": "master",
      "截图（产物/运行结果/对话）": "[图片]",
      "日志轨迹": "未提供详细日志轨迹，见截图"
    },
    {
      "Trae Session ID": "session_958",
      "轮次": "第三轮",
      "User Prompt": "增加进程池的异常处理，某个子进程崩溃时不影响其他进程，并记录错误。使用 imap_unordered 获取结果。",
      "任务类型": "Feature迭代",
      "业务领域": "命令行工具",
      "修改范围": "模块内多文件",
      "任务是否完成": "未完成任务",
      "产物及过程是否满意": "不满意",
      "不满意原因": "产物不满意：使用 imap_unordered 时未设置 chunksize，默认分块过大，长尾任务导致最后一个进程卡顿很久（性能边界，与一个 chunk 出错其他继续并行度不符）。worker 异常未 collect 到主进程汇总（部分功能异常）。pool.terminate vs close 未说明（资源边界）。",
      "github地址": "https://github.com/xiaoyu-li-china/test_dogfooding/tree/main/packages",
      "分支/文件夹": "master",
      "截图（产物/运行结果/对话）": "[图片]",
      "日志轨迹": "未提供详细日志轨迹，见截图"
    },
    {
      "Trae Session ID": "session_959",
      "轮次": "第四轮",
      "User Prompt": "为多进程计算函数编写单元测试，使用 unittest.mock 模拟耗时任务，测试分块逻辑。",
      "任务类型": "代码测试",
      "业务领域": "命令行工具",
      "修改范围": "模块内多文件",
      "任务是否完成": "未完成任务",
      "产物及过程是否满意": "不满意",
      "不满意原因": "产物不满意：mock 了 pool.map，直接跳过真实并行执行，未测试进程池初始化失败的情况（测试覆盖不全，与分块逻辑需求未对齐）。imap_unordered 异常分支无 case（第三轮未对齐）。Windows spawn 路径未 skip 文档（环境边界）。",
      "github地址": "https://github.com/xiaoyu-li-china/test_dogfooding/tree/main/packages",
      "分支/文件夹": "master",
      "截图（产物/运行结果/对话）": "[图片]",
      "日志轨迹": "未提供详细日志轨迹，见截图"
    },
    {
      "Trae Session ID": "session_960",
      "轮次": "第五轮",
      "User Prompt": "解释 Python 的 GIL 对多进程和多线程的影响，以及什么场景下多进程比多线程更优（CPU 密集型 vs I/O 密集型）。",
      "任务类型": "代码理解",
      "业务领域": "命令行工具",
      "修改范围": "代码理解文档",
      "任务是否完成": "未完成任务",
      "产物及过程是否满意": "不满意",
      "不满意原因": "产物不满意：指出 GIL 仅影响 CPython，但未提及其他解释器如 Jython 无 GIL，表述不够全面（解释不完整，维护误导）。未对比 multiprocessing vs concurrent.futures（扩展缺口）。I/O 密集用 asyncio 替代未提（最佳实践遗漏）。",
      "github地址": "https://github.com/xiaoyu-li-china/test_dogfooding/tree/main/packages",
      "分支/文件夹": "master",
      "截图（产物/运行结果/对话）": "[图片]",
      "日志轨迹": "未提供详细日志轨迹，见截图"
    }
  ]
}
